xcloudforlinux/__init__.py
xcloudforlinux/xcloudforlinux.py
xcloudforlinux/resources/XCloudJDBC-2.10.6.7.jar
xcloudforlinux/resources/XCloudJDBC_SP_Procedure_Parser-0.1.3.jar
xcloudforlinux/resources/libthrift-0.9.2.jar
xcloudforlinux/resources/log4j-1.2.17.jar
xcloudforlinux/resources/lz4-1.3.0.jar
xcloudforlinux/resources/slf4j-api-1.7.5.jar
xcloudforlinux/resources/slf4j-log4j12-1.7.5.jar
xcloudforlinux/resources/slf4j-simple-1.7.5.jar
xcloudforlinux-0.4.3.dist-info/METADATA
xcloudforlinux-0.4.3.dist-info/WHEEL
xcloudforlinux-0.4.3.dist-info/top_level.txt
xcloudforlinux-0.4.3.dist-info/RECORD
