Metadata-Version: 2.1
Name: xcloudforlinux
Version: 0.4.3
Summary: 这是一个国信行云数据库并发查询python程序,主要应用于自动通报
Home-page: https://github.com/bailulue
Author: bailu
Author-email: yabailu@chinatelecom.cn
Requires-Dist: JPype1==1.5.0
Requires-Dist: jinja2==3.1.4
